<?xml version="1.0"?>
<opencv_storage>
<num_disparities>10.</num_disparities>
<block_size>3.0500000000000000e+01</block_size>
<pre_filter_type>0</pre_filter_type>
<pre_filter_size>7.5000000000000000e+00</pre_filter_size>
<pre_filter_cap>10</pre_filter_cap>
<texture_threshold>36</texture_threshold>
<uniqueness_ratio>10</uniqueness_ratio>
<speckle_range>28</speckle_range>
<speckle_window_size>4.</speckle_window_size>
<disparity_max_diff>0</disparity_max_diff>
<min_disparity>0</min_disparity>
<obstacle_area>0.</obstacle_area>
<contour_area>0.</contour_area>
<M>40.</M>
</opencv_storage>
